visor_vari/__init__.py
visor_vari/see.py
visor_vari/visorquipus.py
visor_vari/carpeta_de_apoyo/__init__.py
visor_vari/carpeta_de_apoyo/oper_fucional.py
visor_vari/carpeta_de_apoyo/revisar.py
visor_vari/carpeta_de_apoyo/vent_en_tk.py
visor_vari/carpeta_de_apoyo/canales_de_apoyo/__init__.py
visor_vari/carpeta_de_apoyo/canales_de_apoyo/apoyo_de_revisar.py
visor_vari/carpeta_de_apoyo/opca_s/__init__.py
visor_vari/carpeta_de_apoyo/opca_s/fuentes/__init__.py
visor_vari/carpeta_de_apoyo/opca_s/fuentes/saliendo.py
visor_vari/carpeta_de_apoyo/opca_s/fuentes/script_poci.py
visor_vari/carpeta_de_apoyo/opca_s/gera/__init__.py
visor_vari/carpeta_de_apoyo/opca_s/gera/salida.py
visor_vari/carpeta_de_apoyo/opca_s/gera/script_pociciones.py
visor_vari/mana/__init__.py
visor_vari/mana/elementos_de_conducto/__init__.py
visor_vari/mana/elementos_de_conducto/conducto_cuatro.py
visor_vari/mana/elementos_de_conducto/conducto_dos.py
visor_vari/mana/elementos_de_conducto/conducto_tres.py
visor_vari/mana/elementos_de_conducto/conducto_uno.py
visor_vari/mana/interfases_option/__init__.py
visor_vari/mana/interfases_option/hilo_para_vent.py
visor_vari/mana/interfases_option/tipo_visor_1.py
visor_vari/mana/interfases_option/tipo_visor_2.py
visor_vari/mana/interfases_option/tipo_visor_3.py
visor_vari/mana/interfases_option/tipo_visor_4.py
visor_vari/mana/interfases_option/con_vent_1/__init__.py
visor_vari/mana/interfases_option/con_vent_1/tipo_visor_5.py
visor_vari/mana/interfases_option/con_vent_1/tipo_visor_6.py
visor_vari/mana/interfases_option/con_vent_2/__init__.py
visor_vari/mana/interfases_option/con_vent_2/tipo_visor_7.py
visor_vari/mana/interfases_option/con_vent_2/tipo_visor_8.py
visor_vari/mas_bajo_nivel/__init__.py
visor_vari/mas_bajo_nivel/variables_valores.py
visor_vari/readme_visor/__init__.py
visor_vari/readme_visor/readme.py
visor_vari/readme_visor/readme_tipos.py
visor_vari-1.8.dist-info/licenses/LICENSE.txt
visor_vari-1.8.dist-info/METADATA
visor_vari-1.8.dist-info/WHEEL
visor_vari-1.8.dist-info/top_level.txt
visor_vari-1.8.dist-info/RECORD
