Metadata-Version: 2.4
Name: visor_vari
Version: 1.8
Summary: Permite la visualización de grandes conjuntos de datos en sistemas (software) complejos
Home-page: https://github.com/Metal-Alcyone-zero/visor_vari
Author: El señor es el único eterno. Que la ciencia lo honre a Él
Author-email: from.colombia.to.all@gmail.com
Classifier: Programming Language :: Python :: 3
Classifier: License :: OSI Approved :: Mozilla Public License 2.0 (MPL 2.0)
Classifier: Operating System :: OS Independent
Classifier: Development Status :: 4 - Beta
Classifier: Intended Audience :: Developers
Classifier: Topic :: Software Development :: Debuggers
Requires-Python: >=3.6
License-File: LICENSE.txt
Dynamic: author
Dynamic: author-email
Dynamic: classifier
Dynamic: description
Dynamic: description-content-type
Dynamic: home-page
Dynamic: license-file
Dynamic: requires-python
Dynamic: summary
